OptmPE/Config.json
OptmPE/__init__.py
OptmPE/__main__.py
Optm_ParserEngine-1.1.0.dist-info/LICENSE
Optm_ParserEngine-1.1.0.dist-info/METADATA
Optm_ParserEngine-1.1.0.dist-info/WHEEL
Optm_ParserEngine-1.1.0.dist-info/entry_points.txt
Optm_ParserEngine-1.1.0.dist-info/top_level.txt
Optm_ParserEngine-1.1.0.dist-info/RECORD
