Metadata-Version: 2.1
Name: Optm-ParserEngine
Version: 1.1.0
Summary: Python Regex Parser Engine
Author: Gurmukhnishan Singh
Author-email: info@gurmukhnishansingh.me
License-File: LICENSE
